trytond/modules/health_imaging_worklist/COPYING
trytond/modules/health_imaging_worklist/README.rst
trytond/modules/health_imaging_worklist/__init__.py
trytond/modules/health_imaging_worklist/health_imaging_worklist.py
trytond/modules/health_imaging_worklist/health_imaging_worklist_view.xml
trytond/modules/health_imaging_worklist/locale/ar.po
trytond/modules/health_imaging_worklist/locale/de.po
trytond/modules/health_imaging_worklist/locale/el.po
trytond/modules/health_imaging_worklist/locale/eo.po
trytond/modules/health_imaging_worklist/locale/es.po
trytond/modules/health_imaging_worklist/locale/fr.po
trytond/modules/health_imaging_worklist/locale/health_imaging_worklist.pot
trytond/modules/health_imaging_worklist/locale/it_IT.po
trytond/modules/health_imaging_worklist/locale/ja_JP.po
trytond/modules/health_imaging_worklist/locale/ka.po
trytond/modules/health_imaging_worklist/locale/lo.po
trytond/modules/health_imaging_worklist/locale/pt_BR.po
trytond/modules/health_imaging_worklist/locale/sv.po
trytond/modules/health_imaging_worklist/locale/tr.po
trytond/modules/health_imaging_worklist/locale/uk.po
trytond/modules/health_imaging_worklist/locale/zh_CN.po
trytond/modules/health_imaging_worklist/pyproject.toml
trytond/modules/health_imaging_worklist/tests/__init__.py
trytond/modules/health_imaging_worklist/tests/test_health_imaging_worklist.py
trytond/modules/health_imaging_worklist/tryton.cfg
trytond/modules/health_imaging_worklist/view/imaging_test_form.xml
trytond/modules/health_imaging_worklist/view/imaging_test_request_form.xml
trytond/modules/health_imaging_worklist/view/worklist_template_form.xml
trytond/modules/health_imaging_worklist/view/worklist_template_tree.xml
gnuhealth_imaging_worklist-5.0.2.dist-info/METADATA
gnuhealth_imaging_worklist-5.0.2.dist-info/WHEEL
gnuhealth_imaging_worklist-5.0.2.dist-info/licenses/COPYING
gnuhealth_imaging_worklist-5.0.2.dist-info/RECORD
